html3/__init__.py
html3/html3.py
html3-1.18.dist-info/METADATA
html3-1.18.dist-info/RECORD
html3-1.18.dist-info/WHEEL
html3-1.18.dist-info/top_level.txt
